{
  "hero": "hero_priest",
  "hero_id": 65,
  "name": "Venator",
  "hero_type": "Marksman",
  "complexity": 2,
  "tags": {
    "flavor": [
      "Devout",
      "Arms Expert",
      "Tactical"
    ],
    "playstyle": [
      "marksman"
    ],
    "damage_type": [
      "dot",
      "spirit",
      "bullet"
    ],
    "utility": [
      "slow",
      "stun"
    ]
  },
  "base_stats": {
    "max_move_speed": 6.4,
    "sprint_speed": 1.5,
    "crouch_speed": 4.75,
    "move_acceleration": 4,
    "light_melee_damage": 50,
    "heavy_melee_damage": 125,
    "health": 750,
    "weapon_power": 0,
    "reload_speed": 1,
    "stamina": 3,
    "health_regen": 2,
    "stamina_regen_per_second": 0.222222,
    "spirit_duration": 1,
    "spirit_range": 1,
    "ground_dash_distance_in_meters": 10,
    "ground_dash_duration": 0.7,
    "air_dash_distance_in_meters": 8,
    "air_dash_duration": 0.49
  },
  "scaling_per_level": {
    "base_bullet_damage_from_level": 0.27,
    "health": 38,
    "base_melee_damage_from_level": 1.7,
    "boon_count": 1,
    "spirit__power": 1.1
  },
  "abilities": [
    {
      "id": "ability_priest_flashbang",
      "slot": 1,
      "name": "Consecrating Grenade",
      "description": "Fire a grenade that bounces before exploding, dealing weapon damage and setting enemies on fire. Burning targets deal pure damage to enemies in the area and suffer from reduced healing.",
      "cast_type": "active",
      "targeting": "instant",
      "stats": {
        "cooldown": 25,
        "ability_unit_target_limit": 1,
        "ability_cast_delay": 0.03,
        "ability_post_cast_duration": 0.15,
        "channel_move_speed": -1,
        "radius": "4.5m",
        "damage": 35,
        "camera_turn_rate_max": 15,
        "burn_duration": 3.5,
        "dps": 10,
        "heal_amp_regen_penalty_percent": -30,
        "tick_rate": 0.2,
        "bounce_grenade_speed": 1100,
        "burn_radius": "4.5m",
        "burn_linger_duration": 0.15,
        "heal_amp_receive_penalty_percent": -30,
        "pre_bounce_lifetime": 15,
        "bounce_lifetime": 0.5
      },
      "effects": [
        {
          "type": "bullet_damage",
          "base_value": 35,
          "scales_with": {
            "stat": "base_weapon_damage_increase",
            "ratio": 1.2
          },
          "formula": "35 + (base_weapon_damage_increase * 1.2)",
          "unit": "damage"
        },
        {
          "type": "dot",
          "base_value": 3.5,
          "scales_with": {
            "stat": "spirit_power",
            "ratio": 1
          },
          "formula": "3.5 + (spirit_power * 1)",
          "unit": "damage/sec"
        },
        {
          "type": "dot",
          "base_value": "4.5m",
          "scales_with": {
            "stat": "spirit_power",
            "ratio": 1
          },
          "formula": "4.5m + (spirit_power * 1)",
          "unit": "damage/sec"
        },
        {
          "type": "dot",
          "base_value": 0.15,
          "unit": "damage/sec"
        }
      ],
      "upgrades": []
    },
    {
      "id": "ability_priest_knockback",
      "slot": 2,
      "name": "Gutshot",
      "description": "Fire a blast with your shotgun, dealing weapon damage and pushing enemies back. Enemies near a wall receive stun and take bonus weapon damage.",
      "cast_type": "active",
      "targeting": "target",
      "stats": {
        "cooldown": 23,
        "cast_range": "10m",
        "ability_unit_target_limit": 99,
        "ability_cast_delay": 0.25,
        "ability_cooldown_between_charge": -1,
        "channel_move_speed": -1,
        "damage": 60,
        "bonus_damage": 30,
        "stun_duration": 0.65,
        "knockback_speed": 1200,
        "bonus_knockback_distance": "3.5m",
        "targeting_cone_angle": 60,
        "push_force": 6,
        "self_push_force": 500,
        "max_push_force_horizontal": 1400,
        "max_push_force_vertical": 500,
        "wall_stun_distance": "7m"
      },
      "effects": [
        {
          "type": "bullet_damage",
          "base_value": 60,
          "scales_with": {
            "stat": "base_weapon_damage_increase",
            "ratio": 1
          },
          "formula": "60 + (base_weapon_damage_increase * 1)",
          "unit": "damage"
        },
        {
          "type": "bullet_damage",
          "base_value": 30,
          "scales_with": {
            "stat": "base_weapon_damage_increase",
            "ratio": 0.9
          },
          "formula": "30 + (base_weapon_damage_increase * 0.9)",
          "unit": "damage"
        },
        {
          "type": "stun",
          "base_value": 0.65,
          "scales_with": {
            "stat": "spirit_power",
            "ratio": 1
          },
          "formula": "0.65 + (spirit_power * 1)",
          "unit": "seconds"
        },
        {
          "type": "stun",
          "base_value": "7m",
          "scales_with": {
            "stat": "spirit_power",
            "ratio": 1
          },
          "formula": "7m + (spirit_power * 1)",
          "unit": "seconds"
        }
      ],
      "upgrades": []
    },
    {
      "id": "ability_priest_beartrap",
      "slot": 3,
      "name": "Hex-Lined Snap Trap",
      "description": "Kick a trap that arms after a brief delay. The trap springs on the first enemy it touches, dealing spirit damage, applying immobilize, and revealing enemies for a duration afterwards.",
      "cast_type": "active",
      "targeting": "instant",
      "stats": {
        "cooldown": 25,
        "ability_unit_target_limit": 1,
        "ability_cast_delay": 0.2,
        "ability_charges": 2,
        "ability_cooldown_between_charge": 8,
        "channel_move_speed": -1,
        "radius": "2m",
        "trap_height": "2m",
        "lifetime": 30,
        "damage": 80,
        "immobilize_duration": 1.5,
        "arm_time": 0.5,
        "trip_up_speed": 250,
        "reveal_duration": 6,
        "tick_rate": 0.1,
        "tether_radius": "0.3m",
        "tether_duration": 0.6
      },
      "effects": [
        {
          "type": "spirit_damage",
          "base_value": 80,
          "scales_with": {
            "stat": "spirit_power",
            "ratio": 2.2
          },
          "formula": "80 + (spirit_power * 2.2)",
          "unit": "damage"
        }
      ],
      "upgrades": []
    },
    {
      "id": "ability_priest_weaponswap",
      "slot": 4,
      "name": "Ira Domini",
      "description": "Load your crossbow with 3 stakes, dealing massively increased weapon damage.The final stake is blessed, dealing bonus pure damage and executing low-health enemies.",
      "cast_type": "active",
      "targeting": "instant",
      "stats": {
        "cooldown": 140,
        "duration": 15,
        "ability_unit_target_limit": 1,
        "ability_cast_delay": 0.3,
        "ability_cooldown_between_charge": -1,
        "channel_move_speed": -1,
        "damage": 120,
        "xecute_threshold": 8,
        "push_force": 500,
        "xplode_radius": "0.2m",
        "swap_end_delay": 0.6,
        "stake_count": 3,
        "bonus_damage": 100,
        "bonus_amp_to_vampire": 5,
        "bonus_move_speed": "0m"
      },
      "effects": [
        {
          "type": "bullet_damage",
          "base_value": 120,
          "scales_with": {
            "stat": "base_weapon_damage_increase",
            "ratio": 1.5
          },
          "formula": "120 + (base_weapon_damage_increase * 1.5)",
          "unit": "damage"
        },
        {
          "type": "slow",
          "base_value": 0,
          "scales_with": {
            "stat": "spirit_power",
            "ratio": 1
          },
          "formula": "0 + (spirit_power * 1)",
          "unit": "%"
        },
        {
          "type": "bullet_damage",
          "base_value": 100,
          "scales_with": {
            "stat": "level__up__boons",
            "ratio": 3
          },
          "formula": "100 + (level__up__boons * 3)",
          "unit": "damage"
        }
      ],
      "upgrades": []
    }
  ],
  "weapon": {
    "id": "citadel_weapon_priest_set",
    "bullet_damage": 8,
    "rounds_per_sec": 7.94,
    "clip_size": 33,
    "reload_time": 2.8,
    "bullet_speed": 62500,
    "bullets_per_shot": 1,
    "bullet_gravity": 0,
    "spread": 0.12,
    "standing_spread": 1.5,
    "inherit_shooter_velocity": 0,
    "falloff_range": [
      787,
      2000
    ],
    "falloff_scale": [
      1,
      0.1
    ],
    "falloff_bias": 0.5,
    "crit_bonus": 1.65,
    "crit_range": [
      500,
      1500
    ],
    "can_zoom": false,
    "attributes": []
  },
  "good_items": [
    {
      "id": "upgrade_active_reload",
      "name": "Active Reload"
    },
    {
      "id": "upgrade_banshee_slugs",
      "name": "Crippling Headshot"
    },
    {
      "id": "upgrade_berserker",
      "name": "Berserker"
    },
    {
      "id": "upgrade_blitz_bullets",
      "name": "Swift Striker"
    },
    {
      "id": "upgrade_bulletshredimbue",
      "name": "Ballistic Enchantment"
    },
    {
      "id": "upgrade_burst_fire",
      "name": "Burst Fire"
    },
    {
      "id": "upgrade_cardio_calibrator",
      "name": "Enduring Speed"
    },
    {
      "id": "upgrade_clip_size",
      "name": "Extended Magazine"
    },
    {
      "id": "upgrade_close_quarter_combat",
      "name": "Point Blank"
    },
    {
      "id": "upgrade_close_range",
      "name": "Close Quarters"
    },
    {
      "id": "upgrade_cooldown_reduction",
      "name": "Superior Cooldown"
    },
    {
      "id": "upgrade_critshot",
      "name": "Lucky Shot"
    },
    {
      "id": "upgrade_damage_recycler",
      "name": "Leech"
    },
    {
      "id": "upgrade_endurance",
      "name": "Extra Regen"
    },
    {
      "id": "upgrade_extra_charge",
      "name": "Extra Charge"
    },
    {
      "id": "upgrade_fervor",
      "name": "Frenzy"
    },
    {
      "id": "upgrade_fleetfoot_boots",
      "name": "Fleetfoot"
    },
    {
      "id": "upgrade_glass_cannon",
      "name": "Glass Cannon"
    },
    {
      "id": "upgrade_headshot_booster",
      "name": "Headshot Booster"
    },
    {
      "id": "upgrade_health_stimpak",
      "name": "Healing Rite"
    },
    {
      "id": "upgrade_hollow_point_rounds",
      "name": "Hollow Point"
    },
    {
      "id": "upgrade_improved_stamina",
      "name": "Extra Stamina"
    },
    {
      "id": "upgrade_inhibitor",
      "name": "Inhibitor"
    },
    {
      "id": "upgrade_intensifying_clip",
      "name": "Intensifying Magazine"
    },
    {
      "id": "upgrade_juggernaut",
      "name": "Juggernaut"
    },
    {
      "id": "upgrade_kinetic_sash",
      "name": "Kinetic Dash"
    },
    {
      "id": "upgrade_magic_tempo",
      "name": "Compress Cooldown"
    },
    {
      "id": "upgrade_medic_bullets",
      "name": "Restorative Shot"
    },
    {
      "id": "upgrade_non_player_bonus",
      "name": "Monster Rounds"
    },
    {
      "id": "upgrade_non_player_bonus_sacrifice",
      "name": "Cultlist Sacrifice"
    },
    {
      "id": "upgrade_pristine_emblem",
      "name": "Opening Rounds"
    },
    {
      "id": "upgrade_proc_silence",
      "name": "Silencer"
    },
    {
      "id": "upgrade_rapid_recharge",
      "name": "Rapid Recharge"
    },
    {
      "id": "upgrade_rapid_rounds",
      "name": "Rapid Rounds"
    },
    {
      "id": "upgrade_rechargingbullets",
      "name": "Recharging Rush"
    },
    {
      "id": "upgrade_regenerating_bullet_shield",
      "name": "Battle Vest"
    },
    {
      "id": "upgrade_reinforcing_casings",
      "name": "Escalating Resilience"
    },
    {
      "id": "upgrade_ricochet",
      "name": "Ricochet"
    },
    {
      "id": "upgrade_spellbreaker",
      "name": "Spellbreaker"
    },
    {
      "id": "upgrade_sprint_booster",
      "name": "Sprint Boots"
    },
    {
      "id": "upgrade_superior_stamina",
      "name": "Stamina Mastery"
    },
    {
      "id": "upgrade_surging_power",
      "name": "Vampiric Burst"
    },
    {
      "id": "upgrade_tech_purge",
      "name": "Spirit Resilience"
    },
    {
      "id": "upgrade_titan_round",
      "name": "Titanic Magazine"
    },
    {
      "id": "upgrade_toxic_bullets",
      "name": "Toxic Bullets"
    },
    {
      "id": "upgrade_transcendent_cooldown",
      "name": "Transcendent Cooldown"
    },
    {
      "id": "upgrade_vampire",
      "name": "Bullet Lifesteal"
    },
    {
      "id": "upgrade_weighted_shots",
      "name": "Weighted Shots"
    }
  ]
}